.gitignore
README.md
pyproject.toml
service/__init__.py
service/__main__.py
service/_define.py
service/_setup.py
service/_uses.py
service/ext/__init__.py
service/ext/decorators.py
service/ext/endpoint.py
service/ext/middleware.py
service/ext/testing.py
service/fn.py
service/logging/__init__.py
service/logging/formatter.py
service/logging/style.py
service/types/__init__.py
service/types/api.py
service/types/app.py
tests/__init__.py
tests/conftest.py
tests/ext/__init__.py
tests/ext/test_endpoint.py
tests/ext/test_helpers.py
tests/fixtures.py
tests/fn/__init__.py
tests/fn/test_create.py
tests/fn/test_debug.py
tests/fn/test_env_file.py
tests/fn/test_environment.py
tests/fn/test_languages.py
tests/fn/test_on_k8s.py
tests/fn/test_paths.py
tests/fn/test_sentry.py
tests/fn/test_socket.py
tests/fn/test_spec.py
tests/fn/test_testing.py
tests/fn/test_user_settings.py
tests/i18n/__init__.py
tests/i18n/test_translations.py
service_dep-0.1.1.dist-info/WHEEL
service_dep-0.1.1.dist-info/METADATA
service_dep-0.1.1.dist-info/RECORD
