Metadata-Version: 2.1
Name: service-dep
Version: 0.1.1
Summary: 
Author: everhide
Author-email: i.tolkachnikov@gmail.com
Requires-Python: >=3.9,<4.0
Classifier: Programming Language :: Python :: 3
Classifier: Programming Language :: Python :: 3.10
Classifier: Programming Language :: Python :: 3.9
Requires-Dist: Faker (>=13.15.1,<14.0.0)
Requires-Dist: PyYAML (>=6.0,<7.0)
Requires-Dist: Pygments (>=2.12.0,<3.0.0)
Requires-Dist: asgi-lifespan (>=1.0.1,<2.0.0)
Requires-Dist: fastapi (>=0.79.0,<0.80.0)
Requires-Dist: fire (>=0.4.0,<0.5.0)
Requires-Dist: httpx-auth (>=0.15.0,<0.16.0)
Requires-Dist: jsonrpcserver (>=5.0.7,<6.0.0)
Requires-Dist: logging-json (>=0.2.1,<0.3.0)
Requires-Dist: pytest (>=7.1.2,<8.0.0)
Requires-Dist: pytest-asyncio (==0.18.3)
Requires-Dist: pytest-httpx (==0.21.0)
Requires-Dist: pytest-logger (>=0.5.1,<0.6.0)
Requires-Dist: pytest-mock (>=3.8.2,<4.0.0)
Requires-Dist: python-dotenv (>=0.20.0,<0.21.0)
Requires-Dist: python-i18n (>=0.3.9,<0.4.0)
Requires-Dist: sentry-sdk (>=1.9.2,<2.0.0)
Requires-Dist: toml (>=0.10.2,<0.11.0)
Requires-Dist: uvicorn (>=0.17.6,<0.18.0)
Requires-Dist: yarl (>=1.8.1,<2.0.0)
